chainit/__init__.py
chainit/decorator.py
chainit/klass.py
chainit/py.typed
chainit-0.4.0.dist-info/LICENSE
chainit-0.4.0.dist-info/METADATA
chainit-0.4.0.dist-info/WHEEL
chainit-0.4.0.dist-info/RECORD
